src/__init__.py
src/vbox.py
vbox_cli-0.0.2.dist-info/LICENSE
vbox_cli-0.0.2.dist-info/METADATA
vbox_cli-0.0.2.dist-info/WHEEL
vbox_cli-0.0.2.dist-info/entry_points.txt
vbox_cli-0.0.2.dist-info/top_level.txt
vbox_cli-0.0.2.dist-info/RECORD
